trysoma_api_client/__init__.py
trysoma_api_client/api_client.py
trysoma_api_client/api_response.py
trysoma_api_client/configuration.py
trysoma_api_client/exceptions.py
trysoma_api_client/py.typed
trysoma_api_client/rest.py
trysoma_api_client/api/__init__.py
trysoma_api_client/api/a2a_api.py
trysoma_api_client/api/bridge_api.py
trysoma_api_client/api/encryption_api.py
trysoma_api_client/api/environment_variable_api.py
trysoma_api_client/api/identity_api.py
trysoma_api_client/api/internal_api.py
trysoma_api_client/api/secret_api.py
trysoma_api_client/api/task_api.py
trysoma_api_client/api/v1_api.py
trysoma_api_client/models/__init__.py
trysoma_api_client/models/api_key_yaml_config.py
trysoma_api_client/models/bridge_config.py
trysoma_api_client/models/broker_action.py
trysoma_api_client/models/broker_action_one_of.py
trysoma_api_client/models/broker_action_redirect.py
trysoma_api_client/models/broker_state.py
trysoma_api_client/models/configuration_schema.py
trysoma_api_client/models/context_info.py
trysoma_api_client/models/context_info_paginated_response.py
trysoma_api_client/models/create_api_key_params.py
trysoma_api_client/models/create_api_key_response.py
trysoma_api_client/models/create_data_encryption_key_params_route.py
trysoma_api_client/models/create_dek_alias_request.py
trysoma_api_client/models/create_environment_variable_request.py
trysoma_api_client/models/create_message_request.py
trysoma_api_client/models/create_message_response.py
trysoma_api_client/models/create_provider_instance_params_inner.py
trysoma_api_client/models/create_resource_server_credential_params_inner.py
trysoma_api_client/models/create_secret_request.py
trysoma_api_client/models/create_user_auth_flow_config_params.py
trysoma_api_client/models/create_user_auth_flow_config_response.py
trysoma_api_client/models/create_user_credential_params_inner.py
trysoma_api_client/models/credential_config.py
trysoma_api_client/models/data_encryption_key.py
trysoma_api_client-0.0.6.dist-info/METADATA
trysoma_api_client-0.0.6.dist-info/WHEEL
trysoma_api_client-0.0.6.dist-info/top_level.txt
trysoma_api_client-0.0.6.dist-info/RECORD
