Metadata-Version: 2.4
Name: trysoma_api_client
Version: 0.0.6
Summary: soma
Home-page: 
Author: OpenAPI Generator community
Author-email: team@openapitools.org
Project-URL: Repository, https://github.com/trysoma/soma
Keywords: OpenAPI,OpenAPI-Generator,soma
Requires-Python: >=3.9
Requires-Dist: urllib3<3.0.0,>=2.1.0
Requires-Dist: python-dateutil>=2.8.2
Requires-Dist: pydantic>=2
Requires-Dist: typing-extensions>=4.7.1
Requires-Dist: types-python-dateutil>=2.9.0.20251115
Dynamic: author
Dynamic: author-email
